README.rst
setup.cfg
setup.py
src/fuzzytext/__init__.py
src/fuzzytext/core.py
src/fuzzytext.egg-info/PKG-INFO
src/fuzzytext.egg-info/SOURCES.txt
src/fuzzytext.egg-info/dependency_links.txt
src/fuzzytext.egg-info/requires.txt
src/fuzzytext.egg-info/top_level.txt