Metadata-Version: 1.0
Name: fuzzytext
Version: 1.0.2
Summary: Framework for extracting structured data from fuzzy texts using the concept of similar contexts
Home-page: https://github.com/ralan/fuzzytext
Author: Alen Rafagudinov
Author-email: ralan@mail.ru
License: MIT
Keywords: NLP fuzzy extractor parser
Platform: UNKNOWN
